rapids_cli/__init__.py
rapids_cli/_compatibility.py
rapids_cli/cli.py
rapids_cli/config.py
rapids_cli/config.yml
rapids_cli/constants.py
rapids_cli/doctor/__init__.py
rapids_cli/doctor/doctor.py
rapids_cli/doctor/checks/__init__.py
rapids_cli/doctor/checks/cuda_driver.py
rapids_cli/doctor/checks/gpu.py
rapids_cli/doctor/checks/memory.py
rapids_cli/doctor/checks/nvlink.py
rapids_cli/doctor/checks/os.py
rapids_cli/doctor/checks/sdd_nvme.py
rapids_cli/tests/test_cuda.py
rapids_cli-0.1.2.dist-info/licenses/LICENSE
rapids_cli-0.1.2.dist-info/METADATA
rapids_cli-0.1.2.dist-info/WHEEL
rapids_cli-0.1.2.dist-info/entry_points.txt
rapids_cli-0.1.2.dist-info/top_level.txt
rapids_cli-0.1.2.dist-info/RECORD
