Metadata-Version: 2.4
Name: rapids-cli
Version: 0.1.2
Summary: A CLI for RAPIDS
License-Expression: Apache-2.0
Project-URL: Homepage, https://github.com/rapidsai/rapids-cli
Project-URL: Source, https://github.com/rapidsai/rapids-cli
Requires-Python: >=3.10
License-File: LICENSE
Requires-Dist: importlib-metadata>=4.13.0; python_version < "3.12"
Requires-Dist: nvidia-ml-py>=12.0
Requires-Dist: packaging
Requires-Dist: psutil
Requires-Dist: rich
Requires-Dist: rich-click
Provides-Extra: test
Requires-Dist: pytest; extra == "test"
Dynamic: license-file
